status_map_validator/__init__.py
status_map_validator/exceptions.py
status_map_validator-0.5.2.dist-info/LICENSE
status_map_validator-0.5.2.dist-info/METADATA
status_map_validator-0.5.2.dist-info/WHEEL
status_map_validator-0.5.2.dist-info/RECORD
