Metadata-Version: 2.1
Name: status-map-validator
Version: 0.5.2
Summary: Status map (and its transitions) data structure and validations
Home-page: https://github.com/douglaslambertinny/status-map-validator
License: MIT
Keywords: status,map,transition,validation
Author: Douglas Lambertinny
Author-email: douglas.b.dev@gmail.com
Requires-Python: >=3.6.2,<4
Classifier: License :: OSI Approved :: MIT License
Classifier: Programming Language :: Python :: 3
Classifier: Programming Language :: Python :: 3.7
Classifier: Programming Language :: Python :: 3.8
Classifier: Programming Language :: Python :: 3.9
Classifier: Programming Language :: Python :: 3.10
Classifier: Programming Language :: Python :: 3.11
Requires-Dist: networkx (>=2.5)
Project-URL: Repository, https://github.com/douglaslambertinny/status-map-validator
